leanix/__init__.py
leanix/plugin.py
leanix/templates/factsheet.jinja2
leanix/templates/factsheet_material.jinja2
mkdocs_leanix_plugin-1.0.2.dist-info/LICENSE
mkdocs_leanix_plugin-1.0.2.dist-info/METADATA
mkdocs_leanix_plugin-1.0.2.dist-info/WHEEL
mkdocs_leanix_plugin-1.0.2.dist-info/entry_points.txt
mkdocs_leanix_plugin-1.0.2.dist-info/top_level.txt
mkdocs_leanix_plugin-1.0.2.dist-info/RECORD
