Metadata-Version: 2.1
Name: mkdocs-leanix-plugin
Version: 1.0.2
Summary: A MkDocs plugin to import LeanIX data
Home-page: https://github.com/chwebdude/mkdocs-leanix-plugin
Author: Fabrice Andreis
Author-email: fabrice@andreis.dev
License: MIT
Keywords: mkdocs leanix
Platform: UNKNOWN
Classifier: Development Status :: 4 - Beta
Classifier: Intended Audience :: Developers
Classifier: Intended Audience :: Information Technology
Classifier: License :: OSI Approved :: MIT License
Classifier: Programming Language :: Python
Classifier: Programming Language :: Python :: 3 :: Only
Classifier: Programming Language :: Python :: 3.4
Classifier: Programming Language :: Python :: 3.5
Classifier: Programming Language :: Python :: 3.6
Classifier: Programming Language :: Python :: 3.7
Requires-Python: >=3.6
License-File: LICENSE
Requires-Dist: mkdocs (>=1.0.4)
Requires-Dist: requests (>=2.0.0)
Requires-Dist: pyjwt (>=2.0.0)
